gradio_cofoldinginput/__init__.py
gradio_cofoldinginput/cofoldinginput.py
gradio_cofoldinginput/cofoldinginput.pyi
gradio_cofoldinginput/templates/component/index.js
gradio_cofoldinginput/templates/component/style.css
gradio_cofoldinginput/templates/example/index.js
gradio_cofoldinginput/templates/example/style.css
gradio_cofoldinginput-0.0.9.dist-info/METADATA
gradio_cofoldinginput-0.0.9.dist-info/WHEEL
gradio_cofoldinginput-0.0.9.dist-info/RECORD
